{
    "left-node-0": [
        {
            "10.0.1.1": [
                {
                    "meta": true,
                    "start_time": "0",
                    "stop_time": "60"
                },
                {
                    "timestamp": "1616914986.715180",
                    "rtt": "120"
                },
                {
                    "timestamp": "1616914986.916428",
                    "rtt": "121"
                },
                {
                    "timestamp": "1616914987.116687",
                    "rtt": "121"
                },
                {
                    "timestamp": "1616914987.315435",
                    "rtt": "120"
                },
                {
                    "timestamp": "1616914987.543883",
                    "rtt": "148"
                },
                {
                    "timestamp": "1616914987.757203",
                    "rtt": "161"
                },
                {
                    "timestamp": "1616914987.958318",
                    "rtt": "162"
                },
                {
                    "timestamp": "1616914988.161021",
                    "rtt": "164"
                },
                {
                    "timestamp": "1616914988.360607",
                    "rtt": "164"
                },
                {
                    "timestamp": "1616914988.565672",
                    "rtt": "169"
                },
                {
                    "timestamp": "1616914988.764371",
                    "rtt": "167"
                },
                {
                    "timestamp": "1616914988.952045",
                    "rtt": "154"
                },
                {
                    "timestamp": "1616914989.147010",
                    "rtt": "149"
                },
                {
                    "timestamp": "1616914989.334862",
                    "rtt": "137"
                },
                {
                    "timestamp": "1616914989.520956",
                    "rtt": "122"
                },
                {
                    "timestamp": "1616914989.720804",
                    "rtt": "120"
                },
                {
                    "timestamp": "1616914989.922074",
                    "rtt": "121"
                },
                {
                    "timestamp": "1616914990.123958",
                    "rtt": "123"
                },
                {
                    "timestamp": "1616914990.324754",
                    "rtt": "122"
                },
                {
                    "timestamp": "1616914990.524173",
                    "rtt": "121"
                },
                {
                    "timestamp": "1616914990.724722",
                    "rtt": "121"
                },
                {
                    "timestamp": "1616914990.926201",
                    "rtt": "122"
                },
                {
                    "timestamp": "1616914991.131617",
                    "rtt": "127"
                },
                {
                    "timestamp": "1616914991.335003",
                    "rtt": "130"
                },
                {
                    "timestamp": "1616914991.532489",
                    "rtt": "127"
                },
                {
                    "timestamp": "1616914991.736400",
                    "rtt": "131"
                },
                {
                    "timestamp": "1616914991.939836",
                    "rtt": "133"
                },
                {
                    "timestamp": "1616914992.143181",
                    "rtt": "136"
                },
                {
                    "timestamp": "1616914992.342038",
                    "rtt": "134"
                },
                {
                    "timestamp": "1616914992.547006",
                    "rtt": "139"
                },
                {
                    "timestamp": "1616914992.748478",
                    "rtt": "139"
                },
                {
                    "timestamp": "1616914992.951462",
                    "rtt": "142"
                },
                {
                    "timestamp": "1616914993.156419",
                    "rtt": "146"
                },
                {
                    "timestamp": "1616914993.357439",
                    "rtt": "146"
                },
                {
                    "timestamp": "1616914993.560992",
                    "rtt": "148"
                },
                {
                    "timestamp": "1616914993.764535",
                    "rtt": "151"
                },
                {
                    "timestamp": "1616914993.962231",
                    "rtt": "148"
                },
                {
                    "timestamp": "1616914994.167852",
                    "rtt": "153"
                },
                {
                    "timestamp": "1616914994.368968",
                    "rtt": "154"
                },
                {
                    "timestamp": "1616914994.572875",
                    "rtt": "157"
                },
                {
                    "timestamp": "1616914994.775115",
                    "rtt": "158"
                },
                {
                    "timestamp": "1616914994.976197",
                    "rtt": "159"
                },
                {
                    "timestamp": "1616914995.172370",
                    "rtt": "154"
                },
                {
                    "timestamp": "1616914995.370925",
                    "rtt": "151"
                },
                {
                    "timestamp": "1616914995.566335",
                    "rtt": "146"
                },
                {
                    "timestamp": "1616914995.756183",
                    "rtt": "135"
                },
                {
                    "timestamp": "1616914995.944584",
                    "rtt": "123"
                },
                {
                    "timestamp": "1616914996.146290",
                    "rtt": "124"
                },
                {
                    "timestamp": "1616914996.343659",
                    "rtt": "121"
                },
                {
                    "timestamp": "1616914996.548602",
                    "rtt": "125"
                },
                {
                    "timestamp": "1616914996.749923",
                    "rtt": "126"
                },
                {
                    "timestamp": "1616914996.951000",
                    "rtt": "127"
                },
                {
                    "timestamp": "1616914997.154271",
                    "rtt": "129"
                },
                {
                    "timestamp": "1616914997.354435",
                    "rtt": "129"
                },
                {
                    "timestamp": "1616914997.557997",
                    "rtt": "132"
                },
                {
                    "timestamp": "1616914997.761654",
                    "rtt": "135"
                },
                {
                    "timestamp": "1616914997.963874",
                    "rtt": "137"
                },
                {
                    "timestamp": "1616914998.167393",
                    "rtt": "140"
                },
                {
                    "timestamp": "1616914998.368608",
                    "rtt": "141"
                },
                {
                    "timestamp": "1616914998.572166",
                    "rtt": "144"
                },
                {
                    "timestamp": "1616914998.773172",
                    "rtt": "144"
                },
                {
                    "timestamp": "1616914998.975668",
                    "rtt": "146"
                },
                {
                    "timestamp": "1616914999.179156",
                    "rtt": "149"
                },
                {
                    "timestamp": "1616914999.379091",
                    "rtt": "149"
                },
                {
                    "timestamp": "1616914999.585256",
                    "rtt": "154"
                },
                {
                    "timestamp": "1616914999.783705",
                    "rtt": "152"
                },
                {
                    "timestamp": "1616914999.987504",
                    "rtt": "156"
                },
                {
                    "timestamp": "1616915000.192161",
                    "rtt": "159"
                },
                {
                    "timestamp": "1616915000.392108",
                    "rtt": "159"
                },
                {
                    "timestamp": "1616915000.588362",
                    "rtt": "154"
                },
                {
                    "timestamp": "1616915000.784698",
                    "rtt": "150"
                },
                {
                    "timestamp": "1616915000.977213",
                    "rtt": "142"
                },
                {
                    "timestamp": "1616915001.167655",
                    "rtt": "132"
                },
                {
                    "timestamp": "1616915001.365020",
                    "rtt": "129"
                },
                {
                    "timestamp": "1616915001.566568",
                    "rtt": "130"
                },
                {
                    "timestamp": "1616915001.770649",
                    "rtt": "134"
                },
                {
                    "timestamp": "1616915001.961116",
                    "rtt": "123"
                },
                {
                    "timestamp": "1616915002.165588",
                    "rtt": "127"
                },
                {
                    "timestamp": "1616915002.366955",
                    "rtt": "128"
                },
                {
                    "timestamp": "1616915002.570335",
                    "rtt": "131"
                },
                {
                    "timestamp": "1616915002.774004",
                    "rtt": "134"
                },
                {
                    "timestamp": "1616915002.973877",
                    "rtt": "133"
                },
                {
                    "timestamp": "1616915003.177407",
                    "rtt": "136"
                },
                {
                    "timestamp": "1616915003.378573",
                    "rtt": "137"
                },
                {
                    "timestamp": "1616915003.582141",
                    "rtt": "140"
                },
                {
                    "timestamp": "1616915003.784622",
                    "rtt": "142"
                },
                {
                    "timestamp": "1616915003.985432",
                    "rtt": "142"
                },
                {
                    "timestamp": "1616915004.191442",
                    "rtt": "148"
                },
                {
                    "timestamp": "1616915004.391342",
                    "rtt": "146"
                },
                {
                    "timestamp": "1616915004.595065",
                    "rtt": "149"
                },
                {
                    "timestamp": "1616915004.797395",
                    "rtt": "151"
                },
                {
                    "timestamp": "1616915004.999775",
                    "rtt": "153"
                },
                {
                    "timestamp": "1616915005.199653",
                    "rtt": "153"
                },
                {
                    "timestamp": "1616915005.394724",
                    "rtt": "147"
                },
                {
                    "timestamp": "1616915005.595926",
                    "rtt": "147"
                },
                {
                    "timestamp": "1616915005.797043",
                    "rtt": "147"
                },
                {
                    "timestamp": "1616915005.992395",
                    "rtt": "141"
                },
                {
                    "timestamp": "1616915006.189760",
                    "rtt": "138"
                },
                {
                    "timestamp": "1616915006.381280",
                    "rtt": "129"
                },
                {
                    "timestamp": "1616915006.583424",
                    "rtt": "131"
                },
                {
                    "timestamp": "1616915006.783186",
                    "rtt": "129"
                },
                {
                    "timestamp": "1616915006.984602",
                    "rtt": "130"
                },
                {
                    "timestamp": "1616915007.180740",
                    "rtt": "126"
                },
                {
                    "timestamp": "1616915007.385563",
                    "rtt": "129"
                },
                {
                    "timestamp": "1616915007.586608",
                    "rtt": "130"
                },
                {
                    "timestamp": "1616915007.794015",
                    "rtt": "136"
                },
                {
                    "timestamp": "1616915007.992812",
                    "rtt": "134"
                },
                {
                    "timestamp": "1616915008.193653",
                    "rtt": "134"
                },
                {
                    "timestamp": "1616915008.399641",
                    "rtt": "140"
                },
                {
                    "timestamp": "1616915008.603170",
                    "rtt": "142"
                },
                {
                    "timestamp": "1616915008.803570",
                    "rtt": "142"
                },
                {
                    "timestamp": "1616915009.009039",
                    "rtt": "147"
                },
                {
                    "timestamp": "1616915009.209016",
                    "rtt": "148"
                },
                {
                    "timestamp": "1616915009.413058",
                    "rtt": "151"
                },
                {
                    "timestamp": "1616915009.616128",
                    "rtt": "153"
                },
                {
                    "timestamp": "1616915009.817359",
                    "rtt": "153"
                },
                {
                    "timestamp": "1616915010.021302",
                    "rtt": "156"
                },
                {
                    "timestamp": "1616915010.223287",
                    "rtt": "159"
                },
                {
                    "timestamp": "1616915010.426720",
                    "rtt": "161"
                },
                {
                    "timestamp": "1616915010.624139",
                    "rtt": "158"
                },
                {
                    "timestamp": "1616915010.816989",
                    "rtt": "150"
                },
                {
                    "timestamp": "1616915011.020545",
                    "rtt": "153"
                },
                {
                    "timestamp": "1616915011.213240",
                    "rtt": "146"
                },
                {
                    "timestamp": "1616915011.408328",
                    "rtt": "141"
                },
                {
                    "timestamp": "1616915011.608093",
                    "rtt": "140"
                },
                {
                    "timestamp": "1616915011.806013",
                    "rtt": "138"
                },
                {
                    "timestamp": "1616915012.005640",
                    "rtt": "136"
                },
                {
                    "timestamp": "1616915012.207982",
                    "rtt": "139"
                },
                {
                    "timestamp": "1616915012.409025",
                    "rtt": "140"
                },
                {
                    "timestamp": "1616915012.612718",
                    "rtt": "142"
                },
                {
                    "timestamp": "1616915012.816245",
                    "rtt": "145"
                },
                {
                    "timestamp": "1616915013.018660",
                    "rtt": "147"
                },
                {
                    "timestamp": "1616915013.215028",
                    "rtt": "144"
                },
                {
                    "timestamp": "1616915013.416035",
                    "rtt": "145"
                },
                {
                    "timestamp": "1616915013.616121",
                    "rtt": "144"
                },
                {
                    "timestamp": "1616915013.819846",
                    "rtt": "146"
                },
                {
                    "timestamp": "1616915014.009938",
                    "rtt": "136"
                },
                {
                    "timestamp": "1616915014.207606",
                    "rtt": "133"
                },
                {
                    "timestamp": "1616915014.402334",
                    "rtt": "127"
                },
                {
                    "timestamp": "1616915014.605913",
                    "rtt": "130"
                },
                {
                    "timestamp": "1616915014.809081",
                    "rtt": "133"
                },
                {
                    "timestamp": "1616915015.010151",
                    "rtt": "134"
                },
                {
                    "timestamp": "1616915015.213794",
                    "rtt": "137"
                },
                {
                    "timestamp": "1616915015.415086",
                    "rtt": "138"
                },
                {
                    "timestamp": "1616915015.617304",
                    "rtt": "140"
                },
                {
                    "timestamp": "1616915015.823350",
                    "rtt": "145"
                },
                {
                    "timestamp": "1616915016.024569",
                    "rtt": "146"
                },
                {
                    "timestamp": "1616915016.225554",
                    "rtt": "147"
                },
                {
                    "timestamp": "1616915016.430407",
                    "rtt": "150"
                },
                {
                    "timestamp": "1616915016.632748",
                    "rtt": "152"
                },
                {
                    "timestamp": "1616915016.836559",
                    "rtt": "155"
                },
                {
                    "timestamp": "1616915017.037392",
                    "rtt": "156"
                },
                {
                    "timestamp": "1616915017.238580",
                    "rtt": "157"
                },
                {
                    "timestamp": "1616915017.439041",
                    "rtt": "157"
                },
                {
                    "timestamp": "1616915017.644750",
                    "rtt": "162"
                },
                {
                    "timestamp": "1616915017.843294",
                    "rtt": "160"
                },
                {
                    "timestamp": "1616915018.031100",
                    "rtt": "147"
                },
                {
                    "timestamp": "1616915018.225141",
                    "rtt": "142"
                },
                {
                    "timestamp": "1616915018.417818",
                    "rtt": "133"
                },
                {
                    "timestamp": "1616915018.611400",
                    "rtt": "126"
                },
                {
                    "timestamp": "1616915018.814998",
                    "rtt": "129"
                },
                {
                    "timestamp": "1616915019.017361",
                    "rtt": "131"
                },
                {
                    "timestamp": "1616915019.222154",
                    "rtt": "136"
                },
                {
                    "timestamp": "1616915019.422123",
                    "rtt": "136"
                },
                {
                    "timestamp": "1616915019.625822",
                    "rtt": "138"
                },
                {
                    "timestamp": "1616915019.825742",
                    "rtt": "137"
                },
                {
                    "timestamp": "1616915020.025543",
                    "rtt": "136"
                },
                {
                    "timestamp": "1616915020.225366",
                    "rtt": "136"
                },
                {
                    "timestamp": "1616915020.430120",
                    "rtt": "140"
                },
                {
                    "timestamp": "1616915020.631294",
                    "rtt": "141"
                },
                {
                    "timestamp": "1616915020.834824",
                    "rtt": "143"
                },
                {
                    "timestamp": "1616915021.037349",
                    "rtt": "145"
                },
                {
                    "timestamp": "1616915021.238353",
                    "rtt": "146"
                },
                {
                    "timestamp": "1616915021.439481",
                    "rtt": "147"
                },
                {
                    "timestamp": "1616915021.643049",
                    "rtt": "149"
                },
                {
                    "timestamp": "1616915021.835587",
                    "rtt": "141"
                },
                {
                    "timestamp": "1616915022.035870",
                    "rtt": "141"
                },
                {
                    "timestamp": "1616915022.239112",
                    "rtt": "145"
                },
                {
                    "timestamp": "1616915022.439273",
                    "rtt": "145"
                },
                {
                    "timestamp": "1616915022.631774",
                    "rtt": "137"
                },
                {
                    "timestamp": "1616915022.833143",
                    "rtt": "138"
                },
                {
                    "timestamp": "1616915023.033081",
                    "rtt": "137"
                },
                {
                    "timestamp": "1616915023.229074",
                    "rtt": "134"
                },
                {
                    "timestamp": "1616915023.431348",
                    "rtt": "135"
                },
                {
                    "timestamp": "1616915023.630139",
                    "rtt": "133"
                },
                {
                    "timestamp": "1616915023.837318",
                    "rtt": "140"
                },
                {
                    "timestamp": "1616915024.036086",
                    "rtt": "138"
                },
                {
                    "timestamp": "1616915024.239666",
                    "rtt": "142"
                },
                {
                    "timestamp": "1616915024.443238",
                    "rtt": "145"
                },
                {
                    "timestamp": "1616915024.642116",
                    "rtt": "143"
                },
                {
                    "timestamp": "1616915024.837190",
                    "rtt": "138"
                },
                {
                    "timestamp": "1616915025.040485",
                    "rtt": "140"
                },
                {
                    "timestamp": "1616915025.239201",
                    "rtt": "139"
                },
                {
                    "timestamp": "1616915025.443922",
                    "rtt": "143"
                },
                {
                    "timestamp": "1616915025.647520",
                    "rtt": "146"
                },
                {
                    "timestamp": "1616915025.848700",
                    "rtt": "147"
                },
                {
                    "timestamp": "1616915026.053734",
                    "rtt": "150"
                },
                {
                    "timestamp": "1616915026.253781",
                    "rtt": "151"
                },
                {
                    "timestamp": "1616915026.447354",
                    "rtt": "143"
                },
                {
                    "timestamp": "1616915026.644817",
                    "rtt": "140"
                },
                {
                    "timestamp": "1616915026.846216",
                    "rtt": "141"
                },
                {
                    "timestamp": "1616915027.043484",
                    "rtt": "138"
                },
                {
                    "timestamp": "1616915027.244508",
                    "rtt": "140"
                },
                {
                    "timestamp": "1616915027.434693",
                    "rtt": "129"
                },
                {
                    "timestamp": "1616915027.642020",
                    "rtt": "135"
                },
                {
                    "timestamp": "1616915027.840980",
                    "rtt": "133"
                },
                {
                    "timestamp": "1616915028.044217",
                    "rtt": "136"
                },
                {
                    "timestamp": "1616915028.244105",
                    "rtt": "137"
                },
                {
                    "timestamp": "1616915028.440476",
                    "rtt": "132"
                },
                {
                    "timestamp": "1616915028.641504",
                    "rtt": "133"
                },
                {
                    "timestamp": "1616915028.844131",
                    "rtt": "134"
                },
                {
                    "timestamp": "1616915029.050339",
                    "rtt": "140"
                },
                {
                    "timestamp": "1616915029.251309",
                    "rtt": "140"
                },
                {
                    "timestamp": "1616915029.452315",
                    "rtt": "141"
                },
                {
                    "timestamp": "1616915029.655821",
                    "rtt": "143"
                },
                {
                    "timestamp": "1616915029.859398",
                    "rtt": "146"
                },
                {
                    "timestamp": "1616915030.059424",
                    "rtt": "146"
                },
                {
                    "timestamp": "1616915030.261943",
                    "rtt": "148"
                },
                {
                    "timestamp": "1616915030.466402",
                    "rtt": "152"
                },
                {
                    "timestamp": "1616915030.669066",
                    "rtt": "154"
                },
                {
                    "timestamp": "1616915030.870001",
                    "rtt": "155"
                },
                {
                    "timestamp": "1616915031.075835",
                    "rtt": "159"
                },
                {
                    "timestamp": "1616915031.273691",
                    "rtt": "157"
                },
                {
                    "timestamp": "1616915031.477007",
                    "rtt": "160"
                },
                {
                    "timestamp": "1616915031.678020",
                    "rtt": "161"
                },
                {
                    "timestamp": "1616915031.874633",
                    "rtt": "156"
                },
                {
                    "timestamp": "1616915032.073368",
                    "rtt": "154"
                },
                {
                    "timestamp": "1616915032.268353",
                    "rtt": "150"
                },
                {
                    "timestamp": "1616915032.454711",
                    "rtt": "135"
                },
                {
                    "timestamp": "1616915032.653710",
                    "rtt": "134"
                },
                {
                    "timestamp": "1616915032.852432",
                    "rtt": "131"
                },
                {
                    "timestamp": "1616915033.054806",
                    "rtt": "133"
                },
                {
                    "timestamp": "1616915033.248400",
                    "rtt": "127"
                },
                {
                    "timestamp": "1616915033.452457",
                    "rtt": "131"
                },
                {
                    "timestamp": "1616915033.656217",
                    "rtt": "133"
                },
                {
                    "timestamp": "1616915033.854928",
                    "rtt": "131"
                },
                {
                    "timestamp": "1616915034.058386",
                    "rtt": "134"
                },
                {
                    "timestamp": "1616915034.262061",
                    "rtt": "138"
                },
                {
                    "timestamp": "1616915034.463292",
                    "rtt": "139"
                },
                {
                    "timestamp": "1616915034.663315",
                    "rtt": "139"
                },
                {
                    "timestamp": "1616915034.869000",
                    "rtt": "143"
                },
                {
                    "timestamp": "1616915035.071644",
                    "rtt": "145"
                },
                {
                    "timestamp": "1616915035.270186",
                    "rtt": "144"
                },
                {
                    "timestamp": "1616915035.471514",
                    "rtt": "145"
                },
                {
                    "timestamp": "1616915035.665241",
                    "rtt": "138"
                },
                {
                    "timestamp": "1616915035.872593",
                    "rtt": "145"
                },
                {
                    "timestamp": "1616915036.071348",
                    "rtt": "143"
                },
                {
                    "timestamp": "1616915036.270905",
                    "rtt": "143"
                },
                {
                    "timestamp": "1616915036.475968",
                    "rtt": "148"
                },
                {
                    "timestamp": "1616915036.678273",
                    "rtt": "149"
                },
                {
                    "timestamp": "1616915036.879140",
                    "rtt": "149"
                },
                {
                    "timestamp": "1616915037.085197",
                    "rtt": "155"
                },
                {
                    "timestamp": "1616915037.281691",
                    "rtt": "151"
                },
                {
                    "timestamp": "1616915037.466757",
                    "rtt": "136"
                },
                {
                    "timestamp": "1616915037.668081",
                    "rtt": "136"
                },
                {
                    "timestamp": "1616915037.863386",
                    "rtt": "131"
                },
                {
                    "timestamp": "1616915038.066805",
                    "rtt": "134"
                },
                {
                    "timestamp": "1616915038.265484",
                    "rtt": "133"
                },
                {
                    "timestamp": "1616915038.465356",
                    "rtt": "132"
                },
                {
                    "timestamp": "1616915038.666272",
                    "rtt": "133"
                },
                {
                    "timestamp": "1616915038.867378",
                    "rtt": "133"
                },
                {
                    "timestamp": "1616915039.072705",
                    "rtt": "137"
                },
                {
                    "timestamp": "1616915039.274747",
                    "rtt": "140"
                },
                {
                    "timestamp": "1616915039.476921",
                    "rtt": "141"
                },
                {
                    "timestamp": "1616915039.679498",
                    "rtt": "142"
                },
                {
                    "timestamp": "1616915039.872337",
                    "rtt": "135"
                },
                {
                    "timestamp": "1616915040.072871",
                    "rtt": "134"
                },
                {
                    "timestamp": "1616915040.274505",
                    "rtt": "136"
                },
                {
                    "timestamp": "1616915040.478047",
                    "rtt": "139"
                },
                {
                    "timestamp": "1616915040.679083",
                    "rtt": "140"
                },
                {
                    "timestamp": "1616915040.883993",
                    "rtt": "143"
                },
                {
                    "timestamp": "1616915041.084875",
                    "rtt": "144"
                },
                {
                    "timestamp": "1616915041.286239",
                    "rtt": "145"
                },
                {
                    "timestamp": "1616915041.489622",
                    "rtt": "148"
                },
                {
                    "timestamp": "1616915041.684959",
                    "rtt": "143"
                },
                {
                    "timestamp": "1616915041.887166",
                    "rtt": "145"
                },
                {
                    "timestamp": "1616915042.088111",
                    "rtt": "146"
                },
                {
                    "timestamp": "1616915042.289392",
                    "rtt": "147"
                },
                {
                    "timestamp": "1616915042.494494",
                    "rtt": "152"
                },
                {
                    "timestamp": "1616915042.695336",
                    "rtt": "151"
                },
                {
                    "timestamp": "1616915042.894049",
                    "rtt": "149"
                },
                {
                    "timestamp": "1616915043.091457",
                    "rtt": "146"
                },
                {
                    "timestamp": "1616915043.288961",
                    "rtt": "144"
                },
                {
                    "timestamp": "1616915043.491415",
                    "rtt": "146"
                },
                {
                    "timestamp": "1616915043.693492",
                    "rtt": "148"
                },
                {
                    "timestamp": "1616915043.894992",
                    "rtt": "148"
                },
                {
                    "timestamp": "1616915044.086382",
                    "rtt": "139"
                },
                {
                    "timestamp": "1616915044.287493",
                    "rtt": "141"
                },
                {
                    "timestamp": "1616915044.493411",
                    "rtt": "145"
                },
                {
                    "timestamp": "1616915044.692209",
                    "rtt": "143"
                },
                {
                    "timestamp": "1616915044.883566",
                    "rtt": "134"
                },
                {
                    "timestamp": "1616915045.084643",
                    "rtt": "135"
                },
                {
                    "timestamp": "1616915045.280931",
                    "rtt": "131"
                },
                {
                    "timestamp": "1616915045.485643",
                    "rtt": "135"
                },
                {
                    "timestamp": "1616915045.685417",
                    "rtt": "134"
                },
                {
                    "timestamp": "1616915045.882394",
                    "rtt": "130"
                },
                {
                    "timestamp": "1616915046.084200",
                    "rtt": "131"
                },
                {
                    "timestamp": "1616915046.287092",
                    "rtt": "134"
                },
                {
                    "timestamp": "1616915046.487564",
                    "rtt": "134"
                }
            ]
        }
    ]
}